.gitignore
.gitmodules
LICENSE
Makefile
README.rst
pyproject.toml
setup.cfg
setup.py
./microfuse/__init__.py
./microfuse/fuse.py
./microfuse/link.py
./microfuse/multiplex.py
./microfuse/term.py
./microfuse/util/__init__.py
./microfuse/util/_ctx.py
./microfuse/util/_dict.py
./microfuse/util/_event.py
./microfuse/util/_impl.py
./microfuse/util/_main.py
./microfuse/util/_module.py
./microfuse/util/_msg.py
./microfuse/util/_msgpack.py
./microfuse/util/_path.py
./microfuse/util/_queue.py
./microfuse/util/_server.py
./microfuse/util/_spawn.py
./microfuse/util/_systemd.py
./microfuse/util/_yaml.py
doc/file_system.rst
doc/messages.rst
doc/usage.rst
embedded/deps
embedded/msgpack.py
embedded/sched.py
embedded/ufuse.py
microfuse/__init__.py
microfuse/fuse.py
microfuse/link.py
microfuse/multiplex.py
microfuse/term.py
microfuse.egg-info/PKG-INFO
microfuse.egg-info/SOURCES.txt
microfuse.egg-info/dependency_links.txt
microfuse.egg-info/requires.txt
microfuse.egg-info/top_level.txt
microfuse.egg-info/zip-safe
scripts/mpy-cmd
scripts/mpy-link
scripts/mpy-term
scripts/run_test.py
test/client_unix.py
test/deps