Metadata-Version: 2.1
Name: microfuse
Version: 0.2.1
Summary: A FUSE plus MQTT plus REPL channelfor MicroPython
Home-page: https://github.com/M-o-a-T/microfuse
Author: Matthias Urlichs
Author-email: matthias@urlichs.de
Maintainer: Matthias Urlichs
Maintainer-email: <matthias@urlichs.de>
License: GPL v3
Project-URL: Bug Tracker, https://github.com/M-o-a-T/microfuse/issues
Project-URL: Source Code, https://github.com/M-o-a-T/microfuse
Platform: UNKNOWN
Classifier: Development Status :: 4 - Beta
Classifier: Environment :: Console
Classifier: Intended Audience :: Developers
Classifier: Intended Audience :: System Administrators
Classifier: License :: OSI Approved :: GNU General Public License v3 (GPLv3)
Classifier: Operating System :: OS Independent
Classifier: Programming Language :: Python :: 3.7
Classifier: Programming Language :: Python :: 3.8
Classifier: Programming Language :: Python :: 3.9
Classifier: Programming Language :: Python :: Implementation :: MicroPython
Classifier: Topic :: Utilities
Requires-Python: >=3.7
